fifo-model/fifo/fifo_mem_blk.v
module FIFO_MEM_BLK(
    clk,
    writeN,
    wr_addr,
    rd_addr,
    data_in,
    data_out
);

input clk;
input writeN;
input [(`FCWIDTH-1):0] wr_addr; //write address
input [(`FCWIDTH-1):0] rd_addr; //read address
input [(`FWIDTH-1):0] data_in;
output [(`FWIDTH-1):0] data_out;
wire [(`FWIDTH-1):0] data_out;
reg [(`FWIDTH-1):0] FIFO[0:(`FDEPTH-1)]; 

assign data_out = FIFO[rd_addr];
always @(posedge clk)
begin
    if(writeN == 1'b0)
        FIFO[wr_addr] <= data_in;
end
endmodule

fifo-model/fifo/fifo.v
`define FWIDTH 32
`define FDEPTH 4
`define FCWIDTH 2

module FIFO(
    Clk,
    RstN,
    Data_In,
    FClrN,
    FInN,
    FOutN,
    F_Data,
    F_FullN,
    F_LastN,
    F_SLastN,
    F_FirstN,
    F_EmptyN
);

input Clk;
input RstN;
input [(`FWIDTH-1):0] Data_In;
input FInN;
input FClrN;
input FOutN;

output [(`FWIDTH-1):0] F_Data;
output F_FullN;
output F_EmptyN;
output F_LastN;
output F_SLastN;
output F_FirstN;

reg F_FullN;
reg F_EmptyN;
reg F_LastN;
reg F_SLastN;
reg F_FirstN;
reg [`FWIDTH:0] fcounter; //counter indicates num of data in FIFO
reg [`FCWIDTH-1:0] rd_ptr; // 2-bit read pointer
reg [`FCWIDTH-1:0] wr_ptr; // 2-bit write pointer

wire [(`FWIDTH-1):0] FIFODataOut;
wire [(`FWIDTH-1):0] FIFODataIn;
wire ReadN = FOutN;
wire WriteN = FInN;

assign F_Data = FIFODataOut;
assign FIFODataIn = Data_In;

FIFO_MEM_BLK memblk(.clk(CLK),
                    .writeN(WriteN),
                    .data_in(FIFODataIn),
                    .data_out(FIFODataOut),
                    .wr_addr(wr_ptr),
                    .rd_addr(rd_ptr)
);

always @(posedge Clk or negedge RstN)
begin
    if(!RstN) begin
        fcounter <= 0;
        rd_ptr <= 0;
        wr_ptr <= 0;
    end
    else begin
        if(~FClrN)begin
            fcounter <= 0;
            rd_ptr <= 0;
            wr_ptr <= 0;
        end
        else begin
            if(~WriteN)
                wr_ptr <= wr_ptr + 1;
            if(~ReadN)
                rd_ptr <= rd_ptr + 1;
            if(~WriteN && ~ReadN && F_FullN)
                fcounter <= fcounter + 1;
            else if(WriteN && ~ReadN && F_EmptyN)
                fcounter <= fcounter - 1;
        end
    end
end

always @(posedge Clk or negedge RstN)
begin
    if(!RstN)
        F_EmptyN <= 1'b0;
    else begin
        if(FClrN==1'b1) begin
            if(F_EmptyN==1'b0 && WriteN == 1'b0)
                F_EmptyN <= 1'b1;
            else if(F_FirstN == 1'b0 && ReadN == 1'b0 && WriteN == 1'b1)
                F_EmptyN <= 1'b0;
        end
        else 
            F_EmptyN <= 1'b0;
    end
end

always @(posedge Clk or negedge RstN)
begin
    if(!RstN)
        F_FirstN <= 1'b1;
    else begin
        if(FClrN == 1'b1) begin
            if((F_EmptyN==1'b0 && WriteN == 1'b0) || (fcounter==2 && ReadN ==1'b0 && WriteN ==1'b1))
                F_FirstN <= 1'b0;
            else if(F_FirstN==1'b0 && (WriteN ^ ReadN))
                F_FirstN <= 1'b1;
        end
        else begin
            F_FirstN <= 1'b1;
        end
    end
end

always @(posedge Clk or negedge RstN)
begin
    if(!RstN)
        F_SLastN <= 1'b1;
    else begin
        if(FClrN == 1'b1) begin
            if((F_LastN == 1'b0 && ReadN == 1'b0 && WriteN==1'b1) || (fcounter == (`FDEPTH-2) && WriteN==1'b0 && ReadN==1'b1))
                F_SLastN <= 1'b0;
            else if(F_SLastN == 1'b0 && (ReadN ^ WriteN))
                F_SLastN <= 1'b1;
        end
        else 
            F_SLastN <= 1'b1;
    end
end

always @(posedge Clk or negedge RstN)
begin
    if(!RstN)
        F_FullN <= 1'b1;
    else begin
        if(FClrN == 1'b1) begin
            if(F_LastN == 1'b0 && WriteN==1'b0 && ReadN == 1'b1)
                F_FullN <= 1'b0;
            else if(F_FullN == 1'b0 && ReadN == 1'b0)
                F_FullN <= 1'b1;
        end
        else 
            F_FullN <= 1'b1;
    end
end

endmodule

fifo-model/fifo/fifo_tb.v
`timescale 1ns / 1ps
`define FWIDTH 32
`define FDEPTH 4
`define FCWIDTH 2

module fifo_tb;

    reg Clk;
    reg RstN;
    reg [`FWIDTH-1:0] Data_In;
    reg FInN;
    reg FClrN;
    reg FOutN;

    wire [`FWIDTH-1:0] F_Data;
    wire F_FullN;
    wire F_EmptyN;
    wire F_LastN;
    wire F_SLastN;
    wire F_FirstN;

    FIFO uut (
        .Clk(Clk),
        .RstN(RstN),
        .Data_In(Data_In),
        .FClrN(FClrN),
        .FInN(FInN),
        .FOutN(FOutN),
        .F_Data(F_Data),
        .F_FullN(F_FullN),
        .F_EmptyN(F_EmptyN),
        .F_LastN(F_LastN),
        .F_SLastN(F_SLastN),
        .F_FirstN(F_FirstN)
    );

    always #5 Clk = ~Clk; 

    initial begin
        $dumpfile("fifo_tb.vcd"); 
        $dumpvars(0, fifo_tb);

        Clk = 0;
        RstN = 0;
        FClrN = 1;
        FInN = 1;
        FOutN = 1;
        Data_In = 32'h00000000;

        #10 RstN = 1;

        #10 Data_In = 32'hA5A5A5A5; FInN = 0;
        #10 FInN = 1; // Latch Data
        #10 Data_In = 32'h5A5A5A5A; FInN = 0;
        #10 FInN = 1;

        #10 FOutN = 0;
        #10 FOutN = 1;

        #50 FOutN = 0;
        #10 FOutN = 1;

        #100 $finish; 
    end
endmodule

fifo-model/fifo/fifo_tb.vcd
$date
	Sun Feb 23 13:49:51 2025
$end
$version
	Icarus Verilog
$end
$timescale
	1ps
$end
$scope module fifo_tb $end
$var wire 1 ! F_SLastN $end
$var wire 1 " F_LastN $end
$var wire 1 # F_FullN $end
$var wire 1 $ F_FirstN $end
$var wire 1 % F_EmptyN $end
$var wire 32 & F_Data [31:0] $end
$var reg 1 ' Clk $end
$var reg 32 ( Data_In [31:0] $end
$var reg 1 ) FClrN $end
$var reg 1 * FInN $end
$var reg 1 + FOutN $end
$var reg 1 , RstN $end
$scope module uut $end
$var wire 1 - CLK $end
$var wire 1 ' Clk $end
$var wire 32 . Data_In [31:0] $end
$var wire 1 ) FClrN $end
$var wire 32 / FIFODataIn [31:0] $end
$var wire 1 * FInN $end
$var wire 1 + FOutN $end
$var wire 32 0 F_Data [31:0] $end
$var wire 1 1 ReadN $end
$var wire 1 , RstN $end
$var wire 1 2 WriteN $end
$var wire 32 3 FIFODataOut [31:0] $end
$var reg 1 % F_EmptyN $end
$var reg 1 $ F_FirstN $end
$var reg 1 # F_FullN $end
$var reg 1 " F_LastN $end
$var reg 1 ! F_SLastN $end
$var reg 33 4 fcounter [32:0] $end
$var reg 2 5 rd_ptr [1:0] $end
$var reg 2 6 wr_ptr [1:0] $end
$scope module memblk $end
$var wire 1 - clk $end
$var wire 32 7 data_in [31:0] $end
$var wire 32 8 data_out [31:0] $end
$var wire 2 9 rd_addr [1:0] $end
$var wire 2 : wr_addr [1:0] $end
$var wire 1 2 writeN $end
$upscope $end
$upscope $end
$upscope $end
$enddefinitions $end
#0
$dumpvars
b0 :
b0 9
bx 8
b0 7
b0 6
b0 5
b0 4
bx 3
12
11
bx 0
b0 /
b0 .
z-
0,
1+
1*
1)
b0 (
0'
bx &
0%
1$
1#
x"
1!
$end
#5000
1'
#10000
0'
1,
#15000
1'
#20000
0'
02
0*
b10100101101001011010010110100101 /
b10100101101001011010010110100101 7
b10100101101001011010010110100101 (
b10100101101001011010010110100101 .
#25000
0$
1%
b1 6
b1 :
1'
#30000
0'
12
1*
#35000
1'
#40000
0'
02
0*
b1011010010110100101101001011010 /
b1011010010110100101101001011010 7
b1011010010110100101101001011010 (
b1011010010110100101101001011010 .
#45000
1$
b10 6
b10 :
1'
#50000
0'
12
1*
#55000
1'
#60000
0'
01
0+
#65000
b111111111111111111111111111111111 4
b1 5
b1 9
1'
#70000
0'
11
1+
#75000
1'
#80000
0'
#85000
1'
#90000
0'
#95000
1'
#100000
0'
#105000
1'
#110000
0'
#115000
1'
#120000
0'
01
0+
#125000
b111111111111111111111111111111110 4
b10 5
b10 9
1'
#130000
0'
11
1+
