alu/alu.v
module alu(
    input [15:0] A,
    input [15:0] B,
    input [2:0] ALU_Op,
    input [1:0] mode, 
    input clk,
    output reg[15:0] Result,
    output reg Zero,
    output reg Overflow,
    output reg Negative,
    output reg Carry
);

wire[15:0] nota, notb;
assign nota = (mode[0]) ? ~A : A;
assign notb = (mode[1]) ? ~B : B;

always @(posedge clk) begin
    case(ALU_Op)
        3'b000: Result = nota + notb;
        3'b001: Result = nota - notb;
        3'b010: Result = nota & notb;
        3'b011: Result = nota | notb;
        3'b100: Result = nota ^ notb;
        3'b101: Result = nota << 2;
        3'b110: Result = nota >> 2;
        3'b111: Result = (nota < notb) ? 16'b1 : 16'b0;
        default: Result = 16'hxxxx;
    endcase

    Zero = (Result == 16'b0) ? 1 : 0;
    Negative = Result[15];
    Overflow = (ALU_Op == 3'b000 || ALU_Op == 3'b001) && ((nota[15] == notb[15]) && (Result[15] != nota[15]));
end

endmodule

alu/alutlb.v
module alutlb;
    reg [15:0] A, B;
    reg [2:0] ALU_Op;
    reg [1:0] mode;
    reg clk;
    wire [15:0] Result;
    wire Zero, Overflow, Negative, Carry;

    alu uut (
        .A(A),
        .B(B),
        .ALU_Op(ALU_Op),
        .mode(mode),
        .clk(clk),
        .Result(Result),
        .Zero(Zero),
        .Overflow(Overflow),
        .Negative(Negative),
        .Carry(Carry)
    );

    always begin
        #5 clk = ~clk;  
    end

    initial begin
        $dumpfile("alu.vcd");
        $dumpvars(0, alutlb);
        clk = 0;
        A = 16'b0000000000000001;  
        B = 16'b0000000000000010; 
        mode = 2'b00;  
        ALU_Op = 3'b000; 
        
        #10;  
        $display("Test 1: ALU Operation = A + B");
        $display("Result = %b, Zero = %b, Negative = %b, Overflow = %b, Carry = %b", Result, Zero, Negative, Overflow, Carry);

        ALU_Op = 3'b001; 
        #10;
        $display("Test 2: ALU Operation = A - B");
        $display("Result = %b, Zero = %b, Negative = %b, Overflow = %b, Carry = %b", Result, Zero, Negative, Overflow, Carry);

        ALU_Op = 3'b010;  
        #10;
        $display("Test 3: ALU Operation = A & B");
        $display("Result = %b, Zero = %b, Negative = %b, Overflow = %b, Carry = %b", Result, Zero, Negative, Overflow, Carry);

        ALU_Op = 3'b011;  
        #10;
        $display("Test 4: ALU Operation = A | B");
        $display("Result = %b, Zero = %b, Negative = %b, Overflow = %b, Carry = %b", Result, Zero, Negative, Overflow, Carry);

        ALU_Op = 3'b100; 
        #10;
        $display("Test 5: ALU Operation = A XOR B");
        $display("Result = %b, Zero = %b, Negative = %b, Overflow = %b, Carry = %b", Result, Zero, Negative, Overflow, Carry);

        ALU_Op = 3'b101; 
        #10;
        $display("Test 6: ALU Operation = A << 2");
        $display("Result = %b, Zero = %b, Negative = %b, Overflow = %b, Carry = %b", Result, Zero, Negative, Overflow, Carry);

        ALU_Op = 3'b110;  
        #10;
        $display("Test 7: ALU Operation = A >> 2");
        $display("Result = %b, Zero = %b, Negative = %b, Overflow = %b, Carry = %b", Result, Zero, Negative, Overflow, Carry);

        ALU_Op = 3'b111;  
        #10;
        $display("Test 8: ALU Operation = A < B");
        $display("Result = %b, Zero = %b, Negative = %b, Overflow = %b, Carry = %b", Result, Zero, Negative, Overflow, Carry);

        mode = 2'b10; 
        ALU_Op = 3'b000;  
        #10;
        $display("Test 9: ALU Operation = ~A + B");
        $display("Result = %b, Zero = %b, Negative = %b, Overflow = %b, Carry = %b", Result, Zero, Negative, Overflow, Carry);
        
        $finish;
    end
endmodule

alu/alu.vcd
$date
	Fri Feb 07 23:02:00 2025
$end
$version
	Icarus Verilog
$end
$timescale
	1s
$end
$scope module alutlb $end
$var wire 1 ! Zero $end
$var wire 16 " Result [15:0] $end
$var wire 1 # Overflow $end
$var wire 1 $ Negative $end
$var wire 1 % Carry $end
$var reg 16 & A [15:0] $end
$var reg 3 ' ALU_Op [2:0] $end
$var reg 16 ( B [15:0] $end
$var reg 1 ) clk $end
$var reg 2 * mode [1:0] $end
$scope module uut $end
$var wire 16 + A [15:0] $end
$var wire 3 , ALU_Op [2:0] $end
$var wire 16 - B [15:0] $end
$var wire 1 ) clk $end
$var wire 2 . mode [1:0] $end
$var wire 16 / notb [15:0] $end
$var wire 16 0 nota [15:0] $end
$var reg 1 % Carry $end
$var reg 1 $ Negative $end
$var reg 1 # Overflow $end
$var reg 16 1 Result [15:0] $end
$var reg 1 ! Zero $end
$upscope $end
$upscope $end
$enddefinitions $end
#0
$dumpvars
bx 1
b1 0
b10 /
b0 .
b10 -
b0 ,
b1 +
b0 *
0)
b10 (
b0 '
b1 &
x%
x$
x#
bx "
x!
$end
#5
0#
0$
0!
b11 "
b11 1
1)
#10
0)
b1 '
b1 ,
#15
1#
1$
b1111111111111111 "
b1111111111111111 1
1)
#20
0)
b10 '
b10 ,
#25
0#
0$
1!
b0 "
b0 1
1)
#30
0)
b11 '
b11 ,
#35
0!
b11 "
b11 1
1)
#40
0)
b100 '
b100 ,
#45
1)
#50
0)
b101 '
b101 ,
#55
b100 "
b100 1
1)
#60
0)
b110 '
b110 ,
#65
1!
b0 "
b0 1
1)
#70
0)
b111 '
b111 ,
#75
0!
b1 "
b1 1
1)
#80
b1111111111111101 /
0)
b0 '
b0 ,
b10 *
b10 .
#85
1$
b1111111111111110 "
b1111111111111110 1
1)
